nested_grid_plotter/__about__.py
nested_grid_plotter/__init__.py
nested_grid_plotter/animated_plotter.py
nested_grid_plotter/base_plotter.py
nested_grid_plotter/imshow.py
nested_grid_plotter/utils.py
tests/__init__.py
tests/test_animated_plotter.py
tests/test_base_plotter.py
tests/test_examples.py
tests/test_imshow.py
tests/test_utils.py
nested_grid_plotter-1.2.0.dist-info/AUTHORS.rst
nested_grid_plotter-1.2.0.dist-info/LICENSE
nested_grid_plotter-1.2.0.dist-info/METADATA
nested_grid_plotter-1.2.0.dist-info/WHEEL
nested_grid_plotter-1.2.0.dist-info/top_level.txt
nested_grid_plotter-1.2.0.dist-info/RECORD
