Metadata-Version: 2.1
Name: nested_grid_plotter
Version: 1.2.0
Summary: NestedGridPlotter is based on matplotlib and intends to simplify the plotting of nestedgrid by providing a objected oriented class.
Home-page: https://github.com/antoinecollet5/nested_grid_plotter
Author: attr: nested_grid_plotter.__author__
Author-email: antoinecollet5@gmail.com
License: MIT license
Keywords: nested_grid_plotter,matplotlib,plotter,nested grid
Classifier: Development Status :: 2 - Pre-Alpha
Classifier: Intended Audience :: Developers
Classifier: License :: OSI Approved :: MIT License
Classifier: Natural Language :: English
Classifier: Programming Language :: Python :: 3
Classifier: Programming Language :: Python :: 3.7
Classifier: Programming Language :: Python :: 3.8
Classifier: Programming Language :: Python :: 3.9
Classifier: Programming Language :: Python :: 3.10
Classifier: Programming Language :: Python :: 3.11
Classifier: Programming Language :: Python :: 3.12
Requires-Python: <4,>=3.7
License-File: LICENSE
License-File: AUTHORS.rst
Requires-Dist: importlib-metadata
Requires-Dist: numpy
